{
  "main": {
    "id": "b11d23c72148f080",
    "type": "split",
    "children": [
      {
        "id": "5ef504d69950675f",
        "type": "tabs",
        "children": [
          {
            "id": "025fb76189a69a64",
            "type": "leaf",
            "state": {
              "type": "markdown",
              "state": {
                "file": "Attack-Flow===/Attack-Flow-NG.md",
                "mode": "preview",
                "source": false
              },
              "icon": "lucide-file",
              "title": "Attack-Flow-NG"
            }
          }
        ]
      }
    ],
    "direction": "vertical"
  },
  "left": {
    "id": "bf4d2c764279a559",
    "type": "split",
    "children": [
      {
        "id": "7d23a93cc55b90c7",
        "type": "tabs",
        "children": [
          {
            "id": "ef74286d02297a67",
            "type": "leaf",
            "state": {
              "type": "file-explorer",
              "state": {
                "sortOrder": "alphabetical"
              },
              "icon": "lucide-folder-closed",
              "title": "Files"
            }
          },
          {
            "id": "c812a2ec50ad8e8e",
            "type": "leaf",
            "state": {
              "type": "search",
              "state": {
                "query": "rpcclient",
                "matchingCase": true,
                "explainSearch": false,
                "collapseAll": false,
                "extraContext": false,
                "sortOrder": "alphabetical"
              },
              "icon": "lucide-search",
              "title": "Search"
            }
          },
          {
            "id": "b38db3e963442622",
            "type": "leaf",
            "state": {
              "type": "bookmarks",
              "state": {},
              "icon": "lucide-bookmark",
              "title": "Bookmarks"
            }
          }
        ]
      }
    ],
    "direction": "horizontal",
    "width": 355.5
  },
  "right": {
    "id": "c12504f04b728176",
    "type": "split",
    "children": [
      {
        "id": "91560ea365cacac1",
        "type": "tabs",
        "children": [
          {
            "id": "451625aac24ae554",
            "type": "leaf",
            "state": {
              "type": "backlink",
              "state": {
                "file": "Curl.md",
                "collapseAll": false,
                "extraContext": false,
                "sortOrder": "alphabetical",
                "showSearch": false,
                "searchQuery": "",
                "backlinkCollapsed": false,
                "unlinkedCollapsed": true
              },
              "icon": "links-coming-in",
              "title": "Backlinks for Curl"
            }
          },
          {
            "id": "6bdac848c65443fe",
            "type": "leaf",
            "state": {
              "type": "outgoing-link",
              "state": {
                "file": "Socat.md",
                "linksCollapsed": false,
                "unlinkedCollapsed": true
              },
              "icon": "links-going-out",
              "title": "Outgoing links from Socat"
            }
          },
          {
            "id": "4106b70eaf9b9067",
            "type": "leaf",
            "state": {
              "type": "tag",
              "state": {
                "sortOrder": "frequency",
                "useHierarchy": true,
                "showSearch": false,
                "searchQuery": ""
              },
              "icon": "lucide-tags",
              "title": "Tags"
            }
          },
          {
            "id": "f251f015f4523180",
            "type": "leaf",
            "state": {
              "type": "outline",
              "state": {
                "file": "Attack-Flow===/Red-Attack-Flow.md",
                "followCursor": true,
                "showSearch": true,
                "searchQuery": ""
              },
              "icon": "lucide-list",
              "title": "Outline of Red-Attack-Flow"
            }
          }
        ],
        "currentTab": 3
      }
    ],
    "direction": "horizontal",
    "width": 200,
    "collapsed": true
  },
  "left-ribbon": {
    "hiddenItems": {
      "switcher:Open quick switcher": false,
      "graph:Open graph view": false,
      "canvas:Create new canvas": false,
      "daily-notes:Open today's daily note": false,
      "templates:Insert template": false,
      "command-palette:Open command palette": false,
      "zk-prefixer:Create new unique note": false,
      "obsidian-advanced-slides:Show Slide Preview": false
    }
  },
  "active": "025fb76189a69a64",
  "lastOpenFiles": [
    "COMMANDS/FUFF===========Commands.md",
    "Attack-Flow===/Attack-Flow-NG.md",
    "COMMANDS/GOBUSTER========COMMANDS.md",
    "COMMANDS/HTTPIe========CURL.md",
    "COMMANDS/HTTPx================Commands.md",
    "HTB/FootPrinting/SMB.md",
    "COMMANDS/NMAP=========COMMANDS.md",
    "COMMANDS/hashcat=====formats.md",
    "HTB/Password Attacks/Linu Auth/Cred Hunt Linux.md",
    "HTB/Password Attacks/Windows Auth/Credential Hunting in Windows.md",
    "HTB/AD/Password-Policy.md",
    "HTB/AD/Password Spraying - Making a Target User List.md",
    "HTB/Attack-Common-Services/Attacking-SMB.md",
    "Attack-Flow===/Red-Attack-Flow.md",
    "HTB/Password Attacks/Remote-Pasword-Attacks.md",
    "HTB/Password Attacks/Windows Auth/🪟Attacking Windows Credential Manager (Vault-CredMan).md",
    "HTB/File-Transfer/Windows-FileTranfer Method.md",
    "COMMANDS/Nishange===.md",
    "THM hack notes/Metasploit.md",
    "HTB/Shells and Payloads/Windows Exploitation & Enumeration — Summary.md",
    "HTB/Password Attacks/JOHN.md",
    "HTB/Password Attacks/Hash-Cat.md",
    "HTB/Password Attacks/Cracking-Protected-Archives.md",
    "HTB/Password Attacks/🔐 Password Managers & Passwordless Authentication.md",
    "HTB/Password Attacks/Windows Lateral Mov/Pass The Hash.md",
    "HTB/Password Attacks/Windows Lateral Mov/Pass The Cert.md",
    "Attack-Flow===/Defence==Flow",
    "PivotingandTunnelingVisualized.gif",
    "Pasted image 20260511073214.png",
    "Pasted image 20260425112326.png",
    "HTB_Campaign_Notes.zip",
    "zifbpemv",
    "HTB.zip",
    "zi7My4wr",
    "HTB/AD",
    "HTB/Pivoting",
    "HTB/Attack-Common-Services",
    "HTB/Password Attacks/Windows Lateral Mov",
    "HTB/Password Attacks/Network",
    "0-PT-Process.png",
    "images/waffw00f.png",
    "images/sql.png",
    "images/githubpoc.png",
    "images/favico.png",
    "images/dnsrecord.png",
    "images/dnsmap.png"
  ]
}